texttunnel/__init__.py
texttunnel/chat.py
texttunnel/models.py
texttunnel/processor.py
texttunnel/utils.py
texttunnel-0.3.7.dist-info/LICENSE
texttunnel-0.3.7.dist-info/METADATA
texttunnel-0.3.7.dist-info/WHEEL
texttunnel-0.3.7.dist-info/RECORD
