Metadata-Version: 2.1
Name: texttunnel
Version: 0.3.7
Summary: Efficient text processing with the OpenAI API
Home-page: https://github.com/qagentur/texttunnel
License: MIT
Author: Q Agentur für Forschung GmbH
Author-email: info@teamq.de
Requires-Python: >=3.9,<4.0
Classifier: License :: OSI Approved :: MIT License
Classifier: Programming Language :: Python :: 3
Classifier: Programming Language :: Python :: 3.9
Classifier: Programming Language :: Python :: 3.10
Classifier: Programming Language :: Python :: 3.11
Requires-Dist: aiohttp (>=3.8.3,<4.0.0)
Requires-Dist: aiohttp-client-cache (>=0.8.0,<1.0.0)
Requires-Dist: jsonschema (>=3.0.0,<5.0.0)
Requires-Dist: tiktoken (>=0.3.1,<1.0.0)
